setup.cfg
setup.py
mipow/__init__.py
mipow.egg-info/PKG-INFO
mipow.egg-info/SOURCES.txt
mipow.egg-info/dependency_links.txt
mipow.egg-info/not-zip-safe
mipow.egg-info/top_level.txt