Metadata-Version: 1.1
Name: mipow
Version: 0.2
Summary: Python API for controlling Mipow Smart LED bulbs
Home-page: http://github.com/amahlaka/python-mipow
Author: Arttu Mahlakaarto
Author-email: Arttu.mahlakaarto@gmail.com
License: UNKNOWN
Download-URL: https://github.com/amahlaka/python-mipow/tarball/0.2
Platform: UNKNOWN
Classifier: Development Status :: 4 - Beta
Classifier: Intended Audience :: Developers
Classifier: License :: OSI Approved :: MIT License
Classifier: Operating System :: OS Independent
Classifier: Programming Language :: Python
